LICENSE
MANIFEST.in
README.md
TDLPACK.md
TdlpackIO.py
create_docs.sh
setup.py
docs/TdlpackIO.html
docs/index.html
docs/pytdlpack/index.html
docs/pytdlpack/version.html
pytdlpack/__init__.py
pytdlpack/_grid_definitions.py
pytdlpack/_pytdlpack.py
pytdlpack/version.py
pytdlpack.egg-info/PKG-INFO
pytdlpack.egg-info/SOURCES.txt
pytdlpack.egg-info/dependency_links.txt
pytdlpack.egg-info/requires.txt
pytdlpack.egg-info/top_level.txt
pytdlpack/__pycache__/__init__.cpython-38.pyc
pytdlpack/__pycache__/_grid_definitions.cpython-38.pyc
pytdlpack/__pycache__/_pytdlpack.cpython-38.pyc
pytdlpack/__pycache__/version.cpython-38.pyc
sampledata/blend.analysisgrconst.co.ra
sampledata/gfspkd47.2017020100.sq
sampledata/hre201701.sq
tdlpack/arinit.f
tdlpack/bswap.f
tdlpack/ckfilend.f
tdlpack/ckraend.f
tdlpack/cksysend.f
tdlpack/clfilm.f
tdlpack/clfm.f
tdlpack/closefile.f90
tdlpack/createra.f90
tdlpack/fileaction.f
tdlpack/flopnm.f
tdlpack/gridij_to_latlon.f90
tdlpack/latlon_to_gridij.f90
tdlpack/lmijll.f
tdlpack/lmllij.f
tdlpack/mcijll.f
tdlpack/mcllij.f
tdlpack/openfile.f90
tdlpack/openlog.f90
tdlpack/pack.f
tdlpack/pack1d.f
tdlpack/pack2d.f
tdlpack/packgp.f
tdlpack/packxx.f
tdlpack/packyy.f
tdlpack/pkbg.f
tdlpack/pkc4lx.f
tdlpack/pkms00.f
tdlpack/pkms97.f
tdlpack/pkms99.f
tdlpack/pks4lx.f
tdlpack/psijll.f
tdlpack/psllij.f
tdlpack/rddatm.f
tdlpack/rddatmc.f
tdlpack/rdkeym.f
tdlpack/rdtdlm.f
tdlpack/rdtdlmc.f
tdlpack/rdtm.f
tdlpack/rdtmc.f
tdlpack/readfile.f90
tdlpack/reduce.f
tdlpack/tdlpack.pyf
tdlpack/trail.f
tdlpack/unpack.f
tdlpack/unpkbg.f
tdlpack/unpklx.f
tdlpack/unpkoo.f
tdlpack/unpkpo.f
tdlpack/unpkps.f
tdlpack/wrdatm.f
tdlpack/wrdatmc.f
tdlpack/writefile.f90
tdlpack/writep.f
tdlpack/wrkeym.f
tdlpack/wrtdlm.f
tdlpack/wrtdlmc.f
tdlpack/wrtm.f
tdlpack/wrtmc.f
test/test_create_new_grid.py
test/test_create_new_station.py
test/test_read_randomaccess.py
test/test_read_sequential.py
test/test_tdlpackio_fetch.py
test/test_tdlpackio_iter.py