Metadata-Version: 2.1
Name: pytdlpack
Version: 1.0.7
Summary: Python interface for reading and writing TDLPACK data
Home-page: https://github.com/eengl/pytdlpack
Download-URL: https://github.com/eengl/pytdlpack/releases
Author: Eric Engle
Author-email: eric.engle@mac.com
License: GPL-3.0
Classifier: Development Status :: 5 - Production/Stable
Classifier: Programming Language :: Python :: 3
Classifier: Programming Language :: Python :: 3.6
Classifier: Programming Language :: Python :: 3.7
Classifier: Programming Language :: Python :: 3.8
Classifier: Programming Language :: Python :: 3.9
Classifier: Programming Language :: Python :: 3.10
Classifier: Environment :: Console
Classifier: Topic :: Scientific/Engineering
Classifier: Topic :: Scientific/Engineering :: Atmospheric Science
Classifier: Intended Audience :: Science/Research
Classifier: Operating System :: OS Independent
Classifier: License :: OSI Approved :: GNU General Public License v3 (GPLv3)
Requires-Python: >=3.6
License-File: LICENSE
